bookvid2pdf/__init__.py
bookvid2pdf/utils.py
bookvid2pdf-0.1.0.dist-info/METADATA
bookvid2pdf-0.1.0.dist-info/WHEEL
bookvid2pdf-0.1.0.dist-info/RECORD
